Workbook

Sheet Comp Table
A1: ($ in millions) | B1: DoorDash | C1: Uber | D1: Instacart
A2: Operating Income
A3: 2023 | B3: -579000000 | C3: 1110000000 | D3: -2142000000
A4: 2024 | B4: -38000000 | C4: 2799000000 | D4: 489000000
A5: 2025 | B5: 723000000 | C5: 5565000000 | D5: 498000000
A7: Net Income
A8: 2023 | B8: -558000000 | C8: 1887000000 | D8: -1622000000
A9: 2024 | B9: 123000000 | C9: 9856000000 | D9: 457000000
A10: 2025 | B10: 935000000 | C10: 10053000000 | D10: 447000000

Sheet DoorDash Forecast
A1: DoorDash — Operating Income Forecast | E1: Click Button to switch Case by Case basis
A2: ($ in millions) | C2: Active Scenario: | E2: Base
B3: 2025A | C3: 2026E | D3: 2027E | E3: 2028E
A4: Assumptions
A5: Revenue Growth % | C5: =INDEX(B$16:B$18,MATCH($E$2,$A$16:$A$18,0)) -> 0.18 | D5: =INDEX(C$16:C$18,MATCH($E$2,$A$16:$A$18,0)) -> 0.15 | E5: =INDEX(D$16:D$18,MATCH($E$2,$A$16:$A$18,0)) -> 0.12
A6: Operating Margin % | C6: =INDEX(E$16:E$18,MATCH($E$2,$A$16:$A$18,0)) -> 0.025 | D6: =INDEX(F$16:F$18,MATCH($E$2,$A$16:$A$18,0)) -> 0.05 | E6: =INDEX(G$16:G$18,MATCH($E$2,$A$16:$A$18,0)) -> 0.08
A8: Forecast
A9: Revenue | B9: 13717000000 | C9: =B9*(1+C5) -> 16186060000 | D9: =C9*(1+D5) -> 18613969000 | E9: =D9*(1+E5) -> 2.0847645e+10
A10: % Growth | C10: =C9/B9-1 -> 0.18 | D10: =D9/C9-1 -> 0.15 | E10: =E9/D9-1 -> 0.12
A11: Operating Income | B11: ='Comp Table'!B5 -> 723000000 | C11: =C9*C6 -> 404651500 | D11: =D9*D6 -> 930698450 | E11: =E9*E6 -> 1.6678116e+09
A12: Operating Margin | B12: =B11/B9 -> 0.052708318 | C12: =C11/C9 -> 0.025 | D12: =D11/D9 -> 0.05 | E12: =E11/E9 -> 0.08
A14: Scenario Assumptions
A15: Scenario | B15: Grw 2026E | C15: Grw 2027E | D15: Grw 2028E | E15: Mgn 2026E | F15: Mgn 2027E | G15: Mgn 2028E
A16: Base | B16: 0.18 | C16: 0.15 | D16: 0.12 | E16: 0.025 | F16: 0.05 | G16: 0.08
A17: Conservative | B17: 0.14 | C17: 0.1 | D17: 0.07 | E17: 0.015 | F17: 0.03 | G17: 0.05
A18: Bull | B18: 0.22 | C18: 0.19 | D18: 0.16 | E18: 0.04 | F18: 0.07 | G18: 0.11

Sheet Assumption Scenario
A1: Scenario Assumption Methodology
A3: Base Case
A4: Growth rates (18% → 15% → 12%) reflect DoorDash's historical 15-18% YoY growth trajectory, with modest deceleration as the business matures and market saturation moderates demand. Margins (2.5% → 5.0% → 8.0%) are grounded in the company's inflection to profitability in 2025 ($723M operating income, ~5% of revenue), with the assumption that operational leverage from scale drives 200-300 bps of annual margin expansion as take-rate optimization and marketing efficiency improve.
A6: Conservative Case
A7: Assumes more aggressive market saturation and competitive pressure (Uber, Amazon) compress growth to 14% → 10% → 7%. Margin expansion slows to 150-200 bps annually (1.5% → 3.0% → 5.0%), reflecting pricing pressure and higher customer acquisition costs in a crowded market. This case grounds to Q4 2025 performance and accounts for macro headwinds.
A9: Bull Case
A10: Assumes DoorDash sustains 20%+ growth through international expansion and adjacent services (ghost kitchens, advertising revenue), with margins expanding faster (250-400 bps annually to 11% by 2028) as advertising becomes a higher-margin business line (see Uber's success: advertising now a meaningful share of Mobility take-rate). This case reflects best-in-class execution and network effects.
A12: Data Sources
A13: Historical financial data — Form 10-K filings (FY2023–FY2025), SEC EDGAR: • DoorDash, Inc. • Uber Technologies, Inc. • Instacart (Maplebear Inc.) DoorDash FY2025 total revenue ($13,717M) per FY2025 Form 10-K. Source: https://www.sec.gov/cgi-bin/browse-edgar

Sheet Summary
A1: DoorDash — Investment Summary
A2: ($ in millions)
A4: Investment Thesis
A5: DoorDash reached net profitability in 2024 (+$123M net income) after years of losses, then inflected to its first full-year operating profit of $723M in 2025. Among the three comps, Uber reached operating profitability first (2023) and Instacart in 2024; DoorDash was last to cross into operating profit but shows the steepest margin-expansion trajectory, a ~$760M swing in operating income from 2024 to 2025. Suggesting operational leverage from scale and marketplace efficiency gains. If DoorDash sustains 2.5–5% operating margins through 2026–2027, operating income would run roughly $400–900M annually (Base case), comparable to Instacart's normalized profitability despite DoorDash's larger revenue base and greater exposure to delivery competition.
A7: Operating Income — Peer Comparison
B8: 2023A | C8: 2024A | D8: 2025A
A9: DoorDash | B9: ='Comp Table'!B3 -> -579000000 | C9: ='Comp Table'!B4 -> -38000000 | D9: ='Comp Table'!B5 -> 723000000
A10: Uber | B10: ='Comp Table'!C3 -> 1110000000 | C10: ='Comp Table'!C4 -> 2799000000 | D10: ='Comp Table'!C5 -> 5565000000
A11: Instacart | B11: ='Comp Table'!D3 -> -2142000000 | C11: ='Comp Table'!D4 -> 489000000 | D11: ='Comp Table'!D5 -> 498000000
A13: DoorDash Operating Income Forecast (Base Case)
B14: 2026E | C14: 2027E | D14: 2028E
A15: Operating Income | B15: ='DoorDash Forecast'!C11 -> 404651500 | C15: ='DoorDash Forecast'!D11 -> 930698450 | D15: ='DoorDash Forecast'!E11 -> 1.6678116e+09
A16: Operating Margin | B16: ='DoorDash Forecast'!C12 -> 0.025 | C16: ='DoorDash Forecast'!D12 -> 0.05 | D16: ='DoorDash Forecast'!E12 -> 0.08
